odoo/addons/l10n_it_invoices_data_communication_fatturapa/README.rst
odoo/addons/l10n_it_invoices_data_communication_fatturapa/__init__.py
odoo/addons/l10n_it_invoices_data_communication_fatturapa/__manifest__.py
odoo/addons/l10n_it_invoices_data_communication_fatturapa/i18n/it.po
odoo/addons/l10n_it_invoices_data_communication_fatturapa/i18n/l10n_it_invoices_data_communication_fatturapa.pot
odoo/addons/l10n_it_invoices_data_communication_fatturapa/models/__init__.py
odoo/addons/l10n_it_invoices_data_communication_fatturapa/models/communication.py
odoo/addons/l10n_it_invoices_data_communication_fatturapa/readme/CONTRIBUTORS.rst
odoo/addons/l10n_it_invoices_data_communication_fatturapa/readme/DESCRIPTION.rst
odoo/addons/l10n_it_invoices_data_communication_fatturapa/static/description/icon.png
odoo/addons/l10n_it_invoices_data_communication_fatturapa/static/description/index.html
odoo/addons/l10n_it_invoices_data_communication_fatturapa/views/communication_view.xml
odoo14_addon_l10n_it_invoices_data_communication_fatturapa-14.0.1.0.1.dev5.dist-info/METADATA
odoo14_addon_l10n_it_invoices_data_communication_fatturapa-14.0.1.0.1.dev5.dist-info/WHEEL
odoo14_addon_l10n_it_invoices_data_communication_fatturapa-14.0.1.0.1.dev5.dist-info/top_level.txt
odoo14_addon_l10n_it_invoices_data_communication_fatturapa-14.0.1.0.1.dev5.dist-info/RECORD
